ssdnpy/__init__.py
ssdnpy/module1.py
ssdn_1.1-1.0.dist-info/LICENSE.txt
ssdn_1.1-1.0.dist-info/METADATA
ssdn_1.1-1.0.dist-info/WHEEL
ssdn_1.1-1.0.dist-info/top_level.txt
ssdn_1.1-1.0.dist-info/RECORD
