Metadata-Version: 2.1
Name: ssdn-1.1
Version: 1.0
Summary: Symplified Structured Data Notation (SSDN) - Python Package
Home-page: https://github.com/neonek26/SSDN
Author: Štěpán Hofman
Project-URL: Documentation, https://github.com/neonek26/SSDN
Keywords: ssdn,package
Requires-Python: >=3.6
License-File: LICENSE.txt
Provides-Extra: dev
Requires-Dist: check-manifest ; extra == 'dev'
